{
  "translation": {
    "All your favourite MARVEL Movies & Series at one place": "All your favourite MARVEL Movies & Series at one place",
    "Whatch Online or Download Offline": "Whatch Online or Download Offline",
    "Create profiles for diffrent members & get personalised recommendations": "Create profiles for diffrent members & get personalised recommendations",
    "Plans according to your needs at affordable prices": "Plans according to your needs at affordable prices",
    "Let´s Get Started !!!": "Let´s Get Started !!!",
    "Continue": "Continue",
    "Sign Up": "Sign Up",
    "Login": "Login"
  }
}
